streamlabswater/__init__.py
streamlabswater/stream.py
streamlabswater_streamlabswater-0.3.2.dist-info/LICENSE
streamlabswater_streamlabswater-0.3.2.dist-info/METADATA
streamlabswater_streamlabswater-0.3.2.dist-info/WHEEL
streamlabswater_streamlabswater-0.3.2.dist-info/top_level.txt
streamlabswater_streamlabswater-0.3.2.dist-info/RECORD
