Metadata-Version: 2.1
Name: streamlabswater-streamlabswater
Version: 0.3.2
Summary: Python library for the StreamLabs Developer API
Home-page: https://github.com/streamlabswater/stream-python
Author: StreamLabs
Author-email: support@streamlabswater.com
License: MIT
Keywords: streamlabs,streamlabswater,iot,water,sensor,smarthome,automation
Platform: UNKNOWN
Requires-Python: >=3.6
Requires-Dist: requests
